y4/__init__.py
y4/__main__.py
y4/context.py
y4/registry.py
y4/util.py
y4/builtins/__init__.py
y4/builtins/jq.py
y4/builtins/std.py
y4/builtins/xbstrap.py
y4-0.1.1.dist-info/METADATA
y4-0.1.1.dist-info/WHEEL
y4-0.1.1.dist-info/RECORD
